{
  "instrument": "APF",
  "n_spectra_fit": 77,
  "min_snr": 3.5,
  "orders": {
    "3": {
      "echelle_order": 3,
      "model": "sinc2",
      "center_angstrom": 3857.6242038729397,
      "width_angstrom": 28.76496629175191,
      "power": 1.2365609290052875,
      "n_spectra_fit": 77,
      "wavelength_min": 3822.203937,
      "wavelength_max": 3884.401762,
      "rest_line_angstrom": 4861.3,
      "line_mask_half_width_angstrom": 22.0
    },
    "4": {
      "echelle_order": 4,
      "model": "sinc2",
      "center_angstrom": 3916.7151979999994,
      "width_angstrom": 5.0000000000012985,
      "power": 4.499999999999997,
      "n_spectra_fit": 77,
      "wavelength_min": 3853.974256,
      "wavelength_max": 3916.715198,
      "rest_line_angstrom": 4861.3,
      "line_mask_half_width_angstrom": 22.0
    },
    "5": {
      "echelle_order": 5,
      "model": "sinc2",
      "center_angstrom": 3949.5780599999994,
      "width_angstrom": 22.188048921526814,
      "power": 1.2000000000000002,
      "n_spectra_fit": 77,
      "wavelength_min": 3886.384397,
      "wavelength_max": 3949.57806,
      "rest_line_angstrom": 4861.3,
      "line_mask_half_width_angstrom": 22.0
    },
    "6": {
      "echelle_order": 6,
      "model": "sinc2",
      "center_angstrom": 3919.2818842403103,
      "width_angstrom": 17.05806185480667,
      "power": 1.200000000000001,
      "n_spectra_fit": 77,
      "wavelength_min": 3919.281826,
      "wavelength_max": 3982.987623,
      "rest_line_angstrom": 4861.3,
      "line_mask_half_width_angstrom": 22.0
    },
    "7": {
      "echelle_order": 7,
      "model": "sinc2",
      "center_angstrom": 3992.1003180000002,
      "width_angstrom": 35.3481733412596,
      "power": 2.26429400517935,
      "n_spectra_fit": 77,
      "wavelength_min": 3952.597472,
      "wavelength_max": 4016.996263,
      "rest_line_angstrom": 4861.3,
      "line_mask_half_width_angstrom": 22.0
    },
    "8": {
      "echelle_order": 8,
      "model": "sinc2",
      "center_angstrom": 4022.478562005571,
      "width_angstrom": 34.857901666070205,
      "power": 1.4610505608504973,
      "n_spectra_fit": 77,
      "wavelength_min": 3986.767982,
      "wavelength_max": 4051.543222,
      "rest_line_angstrom": 4861.3,
      "line_mask_half_width_angstrom": 22.0
    },
    "9": {
      "echelle_order": 9,
      "model": "sinc2",
      "center_angstrom": 4057.158473527983,
      "width_angstrom": 35.33570160986384,
      "power": 1.4002242143305057,
      "n_spectra_fit": 77,
      "wavelength_min": 4021.363475,
      "wavelength_max": 4086.728035,
      "rest_line_angstrom": 4861.3,
      "line_mask_half_width_angstrom": 22.0
    },
    "10": {
      "echelle_order": 10,
      "model": "sinc2",
      "center_angstrom": 4079.6998979999994,
      "width_angstrom": 34.91903325774992,
      "power": 4.499999999974375,
      "n_spectra_fit": 77,
      "wavelength_min": 4056.572793,
      "wavelength_max": 4122.529248,
      "rest_line_angstrom": 4861.3,
      "line_mask_half_width_angstrom": 22.0
    },
    "11": {
      "echelle_order": 11,
      "model": "sinc2",
      "center_angstrom": 4129.224901299848,
      "width_angstrom": 33.70675357732983,
      "power": 1.2000000000000022,
      "n_spectra_fit": 77,
      "wavelength_min": 4092.397292,
      "wavelength_max": 4158.960499,
      "rest_line_angstrom": 4861.3,
      "line_mask_half_width_angstrom": 22.0
    },
    "12": {
      "echelle_order": 12,
      "model": "sinc2",
      "center_angstrom": 4165.651694550552,
      "width_angstrom": 41.58508935571064,
      "power": 1.953464206520148,
      "n_spectra_fit": 77,
      "wavelength_min": 4128.919421,
      "wavelength_max": 4196.076969,
      "rest_line_angstrom": 4861.3,
      "line_mask_half_width_angstrom": 22.0
    },
    "13": {
      "echelle_order": 13,
      "model": "sinc2",
      "center_angstrom": 4203.339351012941,
      "width_angstrom": 38.14435010751188,
      "power": 1.553032509095886,
      "n_spectra_fit": 77,
      "wavelength_min": 4166.080163,
      "wavelength_max": 4233.788691,
      "rest_line_angstrom": 4861.3,
      "line_mask_half_width_angstrom": 22.0
    },
    "14": {
      "echelle_order": 14,
      "model": "sinc2",
      "center_angstrom": 4241.60789700454,
      "width_angstrom": 51.05344979795768,
      "power": 2.9244335074347068,
      "n_spectra_fit": 77,
      "wavelength_min": 4203.906964,
      "wavelength_max": 4272.217589,
      "rest_line_angstrom": 4861.3,
      "line_mask_half_width_angstrom": 22.0
    },
    "15": {
      "echelle_order": 15,
      "model": "sinc2",
      "center_angstrom": 4279.421917290541,
      "width_angstrom": 42.1856732877761,
      "power": 1.9367490761933854,
      "n_spectra_fit": 77,
      "wavelength_min": 4242.439958,
      "wavelength_max": 4311.360161,
      "rest_line_angstrom": 4861.3,
      "line_mask_half_width_angstrom": 22.0
    },
    "16": {
      "echelle_order": 16,
      "model": "sinc2",
      "center_angstrom": 4318.499829999999,
      "width_angstrom": 57.46437313481751,
      "power": 4.4999999999164295,
      "n_spectra_fit": 77,
      "wavelength_min": 4281.681368,
      "wavelength_max": 4351.212253,
      "rest_line_angstrom": 4861.3,
      "line_mask_half_width_angstrom": 22.0
    },
    "17": {
      "echelle_order": 17,
      "model": "sinc2",
      "center_angstrom": 4362.500195000003,
      "width_angstrom": 56.827361973654554,
      "power": 4.499999998214304,
      "n_spectra_fit": 77,
      "wavelength_min": 4321.62103,
      "wavelength_max": 4391.813962,
      "rest_line_angstrom": 4861.3,
      "line_mask_half_width_angstrom": 22.0
    },
    "18": {
      "echelle_order": 18,
      "model": "sinc2",
      "center_angstrom": 4401.402353666286,
      "width_angstrom": 49.071100147683204,
      "power": 2.295011605203082,
      "n_spectra_fit": 77,
      "wavelength_min": 4362.363869,
      "wavelength_max": 4433.195751,
      "rest_line_angstrom": 4861.3,
      "line_mask_half_width_angstrom": 22.0
    },
    "19": {
      "echelle_order": 19,
      "model": "sinc2",
      "center_angstrom": 4442.5122892361505,
      "width_angstrom": 49.66737929847226,
      "power": 2.3459122816271085,
      "n_spectra_fit": 77,
      "wavelength_min": 4403.850253,
      "wavelength_max": 4475.354106,
      "rest_line_angstrom": 4861.3,
      "line_mask_half_width_angstrom": 22.0
    },
    "20": {
      "echelle_order": 20,
      "model": "sinc2",
      "center_angstrom": 4485.522363308373,
      "width_angstrom": 43.98806424147736,
      "power": 1.679349798248993,
      "n_spectra_fit": 77,
      "wavelength_min": 4446.158032,
      "wavelength_max": 4518.339515,
      "rest_line_angstrom": 4861.3,
      "line_mask_half_width_angstrom": 22.0
    },
    "21": {
      "echelle_order": 21,
      "model": "sinc2",
      "center_angstrom": 4528.242129269958,
      "width_angstrom": 42.167250986173656,
      "power": 1.4011045520096983,
      "n_spectra_fit": 77,
      "wavelength_min": 4489.287957,
      "wavelength_max": 4562.139069,
      "rest_line_angstrom": 4861.3,
      "line_mask_half_width_angstrom": 22.0
    },
    "22": {
      "echelle_order": 22,
      "model": "sinc2",
      "center_angstrom": 4572.751230206596,
      "width_angstrom": 50.66849349567544,
      "power": 2.2003330681197886,
      "n_spectra_fit": 77,
      "wavelength_min": 4533.233563,
      "wavelength_max": 4606.809449,
      "rest_line_angstrom": 4861.3,
      "line_mask_half_width_angstrom": 22.0
    },
    "23": {
      "echelle_order": 23,
      "model": "sinc2",
      "center_angstrom": 4617.950107490079,
      "width_angstrom": 49.33242674905102,
      "power": 1.9800057191635707,
      "n_spectra_fit": 77,
      "wavelength_min": 4578.09562,
      "wavelength_max": 4652.337171,
      "rest_line_angstrom": 4861.3,
      "line_mask_half_width_angstrom": 22.0
    },
    "24": {
      "echelle_order": 24,
      "model": "sinc2",
      "center_angstrom": 4663.902144478064,
      "width_angstrom": 48.16288380201626,
      "power": 1.722250229228859,
      "n_spectra_fit": 77,
      "wavelength_min": 4623.824059,
      "wavelength_max": 4698.820842,
      "rest_line_angstrom": 4861.3,
      "line_mask_half_width_angstrom": 22.0
    },
    "25": {
      "echelle_order": 25,
      "model": "sinc2",
      "center_angstrom": 4711.050889385902,
      "width_angstrom": 49.31517619158875,
      "power": 1.7544172706272436,
      "n_spectra_fit": 77,
      "wavelength_min": 4670.463117,
      "wavelength_max": 4746.20918,
      "rest_line_angstrom": 4861.3,
      "line_mask_half_width_angstrom": 22.0
    },
    "26": {
      "echelle_order": 26,
      "model": "sinc2",
      "center_angstrom": 4758.72703995254,
      "width_angstrom": 47.999958696421615,
      "power": 1.5576758437952163,
      "n_spectra_fit": 77,
      "wavelength_min": 4718.048889,
      "wavelength_max": 4794.573532,
      "rest_line_angstrom": 4861.3,
      "line_mask_half_width_angstrom": 22.0
    },
    "27": {
      "echelle_order": 27,
      "model": "sinc2",
      "center_angstrom": 4807.797993910013,
      "width_angstrom": 51.610987707656264,
      "power": 1.8100736073973729,
      "n_spectra_fit": 77,
      "wavelength_min": 4766.68811,
      "wavelength_max": 4843.932933,
      "rest_line_angstrom": 4861.3,
      "line_mask_half_width_angstrom": 22.0
    },
    "28": {
      "echelle_order": 28,
      "model": "sinc2",
      "center_angstrom": 4857.4935352380435,
      "width_angstrom": 56.15306791964481,
      "power": 2.1614547423612867,
      "n_spectra_fit": 77,
      "wavelength_min": 4816.279851,
      "wavelength_max": 4894.325596,
      "rest_line_angstrom": 4861.3,
      "line_mask_half_width_angstrom": 22.0
    },
    "29": {
      "echelle_order": 29,
      "model": "sinc2",
      "center_angstrom": 4908.754984670542,
      "width_angstrom": 54.902550577289205,
      "power": 1.9019641383109829,
      "n_spectra_fit": 77,
      "wavelength_min": 4866.920432,
      "wavelength_max": 4945.791974,
      "rest_line_angstrom": 4861.3,
      "line_mask_half_width_angstrom": 22.0
    },
    "30": {
      "echelle_order": 30,
      "model": "sinc2",
      "center_angstrom": 4960.653217053506,
      "width_angstrom": 57.39479048883562,
      "power": 2.012937610060654,
      "n_spectra_fit": 77,
      "wavelength_min": 4918.600494,
      "wavelength_max": 4998.343037,
      "rest_line_angstrom": 4861.3,
      "line_mask_half_width_angstrom": 22.0
    },
    "31": {
      "echelle_order": 31,
      "model": "sinc2",
      "center_angstrom": 5013.766291864551,
      "width_angstrom": 52.78674148434567,
      "power": 1.51827996009654,
      "n_spectra_fit": 77,
      "wavelength_min": 4971.43408,
      "wavelength_max": 5052.010409,
      "rest_line_angstrom": 4861.3,
      "line_mask_half_width_angstrom": 22.0
    },
    "32": {
      "echelle_order": 32,
      "model": "sinc2",
      "center_angstrom": 5068.295065088069,
      "width_angstrom": 60.40855680162735,
      "power": 2.030108578472121,
      "n_spectra_fit": 77,
      "wavelength_min": 5025.429912,
      "wavelength_max": 5106.876882,
      "rest_line_angstrom": 4861.3,
      "line_mask_half_width_angstrom": 22.0
    },
    "33": {
      "echelle_order": 33,
      "model": "sinc2",
      "center_angstrom": 5123.60302792363,
      "width_angstrom": 67.1153808346224,
      "power": 2.424271143413965,
      "n_spectra_fit": 77,
      "wavelength_min": 5080.609882,
      "wavelength_max": 5162.907102,
      "rest_line_angstrom": 4861.3,
      "line_mask_half_width_angstrom": 22.0
    },
    "34": {
      "echelle_order": 34,
      "model": "sinc2",
      "center_angstrom": 5180.849896941818,
      "width_angstrom": 52.54898573527374,
      "power": 1.2000000000000002,
      "n_spectra_fit": 77,
      "wavelength_min": 5137.072306,
      "wavelength_max": 5220.191404,
      "rest_line_angstrom": 4861.3,
      "line_mask_half_width_angstrom": 22.0
    },
    "35": {
      "echelle_order": 35,
      "model": "sinc2",
      "center_angstrom": 5238.531841660663,
      "width_angstrom": 76.56962047930143,
      "power": 3.024175919031787,
      "n_spectra_fit": 77,
      "wavelength_min": 5194.712654,
      "wavelength_max": 5278.7506,
      "rest_line_angstrom": 4861.3,
      "line_mask_half_width_angstrom": 22.0
    },
    "36": {
      "echelle_order": 36,
      "model": "sinc2",
      "center_angstrom": 5298.190945297567,
      "width_angstrom": 94.12491632466461,
      "power": 4.499999999999998,
      "n_spectra_fit": 77,
      "wavelength_min": 5253.656854,
      "wavelength_max": 5338.699979,
      "rest_line_angstrom": 4861.3,
      "line_mask_half_width_angstrom": 22.0
    },
    "37": {
      "echelle_order": 37,
      "model": "sinc2",
      "center_angstrom": 5358.75683320039,
      "width_angstrom": 90.36146312835413,
      "power": 3.8214930481235503,
      "n_spectra_fit": 77,
      "wavelength_min": 5314.006871,
      "wavelength_max": 5400.020012,
      "rest_line_angstrom": 4861.3,
      "line_mask_half_width_angstrom": 22.0
    },
    "38": {
      "echelle_order": 38,
      "model": "sinc2",
      "center_angstrom": 5420.865507783169,
      "width_angstrom": 101.44317741339096,
      "power": 4.499999998760795,
      "n_spectra_fit": 77,
      "wavelength_min": 5375.782242,
      "wavelength_max": 5462.749808,
      "rest_line_angstrom": 4861.3,
      "line_mask_half_width_angstrom": 22.0
    },
    "39": {
      "echelle_order": 39,
      "model": "sinc2",
      "center_angstrom": 5484.230928134477,
      "width_angstrom": 78.84020718689656,
      "power": 2.5004304608715233,
      "n_spectra_fit": 77,
      "wavelength_min": 5438.986375,
      "wavelength_max": 5526.881843,
      "rest_line_angstrom": 4861.3,
      "line_mask_half_width_angstrom": 22.0
    },
    "40": {
      "echelle_order": 40,
      "model": "sinc2",
      "center_angstrom": 5549.305127551483,
      "width_angstrom": 89.28169168445025,
      "power": 3.1820873774562246,
      "n_spectra_fit": 77,
      "wavelength_min": 5503.66073,
      "wavelength_max": 5592.625656,
      "rest_line_angstrom": 4861.3,
      "line_mask_half_width_angstrom": 22.0
    },
    "41": {
      "echelle_order": 41,
      "model": "sinc2",
      "center_angstrom": 5616.045047513971,
      "width_angstrom": 108.38910267253225,
      "power": 4.499999990118794,
      "n_spectra_fit": 77,
      "wavelength_min": 5569.847496,
      "wavelength_max": 5659.973287,
      "rest_line_angstrom": 4861.3,
      "line_mask_half_width_angstrom": 22.0
    },
    "42": {
      "echelle_order": 42,
      "model": "sinc2",
      "center_angstrom": 5684.14349364446,
      "width_angstrom": 110.59422405642071,
      "power": 4.4999999999941585,
      "n_spectra_fit": 77,
      "wavelength_min": 5637.664391,
      "wavelength_max": 5728.918384,
      "rest_line_angstrom": 4861.3,
      "line_mask_half_width_angstrom": 22.0
    },
    "43": {
      "echelle_order": 43,
      "model": "sinc2",
      "center_angstrom": 5754.111208341887,
      "width_angstrom": 82.76527413939209,
      "power": 2.2963377001600827,
      "n_spectra_fit": 77,
      "wavelength_min": 5707.174578,
      "wavelength_max": 5799.58807,
      "rest_line_angstrom": 4861.3,
      "line_mask_half_width_angstrom": 22.0
    },
    "44": {
      "echelle_order": 44,
      "model": "sinc2",
      "center_angstrom": 5826.158856038046,
      "width_angstrom": 114.74703857256209,
      "power": 4.499999999950917,
      "n_spectra_fit": 77,
      "wavelength_min": 5778.573849,
      "wavelength_max": 5871.995861,
      "rest_line_angstrom": 4861.3,
      "line_mask_half_width_angstrom": 22.0
    },
    "45": {
      "echelle_order": 45,
      "model": "sinc2",
      "center_angstrom": 5899.451743241252,
      "width_angstrom": 66.69677844315478,
      "power": 1.2000000002842166,
      "n_spectra_fit": 77,
      "wavelength_min": 5851.674397,
      "wavelength_max": 5946.218844,
      "rest_line_angstrom": 4861.3,
      "line_mask_half_width_angstrom": 22.0
    },
    "46": {
      "echelle_order": 46,
      "model": "sinc2",
      "center_angstrom": 5974.553748870719,
      "width_angstrom": 122.01910970775091,
      "power": 4.499999868888628,
      "n_spectra_fit": 77,
      "wavelength_min": 5926.609971,
      "wavelength_max": 6022.403624,
      "rest_line_angstrom": 4861.3,
      "line_mask_half_width_angstrom": 22.0
    },
    "47": {
      "echelle_order": 47,
      "model": "sinc2",
      "center_angstrom": 6052.103929795241,
      "width_angstrom": 124.54815593931544,
      "power": 4.49999999974902,
      "n_spectra_fit": 77,
      "wavelength_min": 6003.595542,
      "wavelength_max": 6100.535559,
      "rest_line_angstrom": 4861.3,
      "line_mask_half_width_angstrom": 22.0
    },
    "48": {
      "echelle_order": 48,
      "model": "sinc2",
      "center_angstrom": 6131.1380060164665,
      "width_angstrom": 128.05683530142832,
      "power": 4.4999999999991624,
      "n_spectra_fit": 77,
      "wavelength_min": 6082.523725,
      "wavelength_max": 6180.706211,
      "rest_line_angstrom": 4861.3,
      "line_mask_half_width_angstrom": 22.0
    },
    "49": {
      "echelle_order": 49,
      "model": "sinc2",
      "center_angstrom": 6212.546842060535,
      "width_angstrom": 130.4991765044527,
      "power": 4.499999999623605,
      "n_spectra_fit": 77,
      "wavelength_min": 6163.550826,
      "wavelength_max": 6263.047359,
      "rest_line_angstrom": 4861.3,
      "line_mask_half_width_angstrom": 22.0
    },
    "50": {
      "echelle_order": 50,
      "model": "sinc2",
      "center_angstrom": 6296.526912686469,
      "width_angstrom": 96.70650096465044,
      "power": 2.1815418189974456,
      "n_spectra_fit": 77,
      "wavelength_min": 6246.786645,
      "wavelength_max": 6347.589717,
      "rest_line_angstrom": 4861.3,
      "line_mask_half_width_angstrom": 22.0
    },
    "51": {
      "echelle_order": 51,
      "model": "sinc2",
      "center_angstrom": 6382.226304223759,
      "width_angstrom": 137.9718186480135,
      "power": 4.499999999751302,
      "n_spectra_fit": 77,
      "wavelength_min": 6332.328988,
      "wavelength_max": 6434.371556,
      "rest_line_angstrom": 4861.3,
      "line_mask_half_width_angstrom": 22.0
    },
    "52": {
      "echelle_order": 52,
      "model": "sinc2",
      "center_angstrom": 6470.054690484023,
      "width_angstrom": 130.80624819986122,
      "power": 3.74775871597996,
      "n_spectra_fit": 77,
      "wavelength_min": 6420.146739,
      "wavelength_max": 6523.760306,
      "rest_line_angstrom": 4861.3,
      "line_mask_half_width_angstrom": 22.0
    },
    "54": {
      "echelle_order": 54,
      "model": "sinc2",
      "center_angstrom": 6654.231361143728,
      "width_angstrom": 108.26278370303358,
      "power": 2.271495719704112,
      "n_spectra_fit": 77,
      "wavelength_min": 6603.318948,
      "wavelength_max": 6710.008905,
      "rest_line_angstrom": 4861.3,
      "line_mask_half_width_angstrom": 22.0
    },
    "55": {
      "echelle_order": 55,
      "model": "sinc2",
      "center_angstrom": 6749.9667072532975,
      "width_angstrom": 106.97753998518074,
      "power": 2.112607252228453,
      "n_spectra_fit": 77,
      "wavelength_min": 6699.006052,
      "wavelength_max": 6807.121782,
      "rest_line_angstrom": 4861.3,
      "line_mask_half_width_angstrom": 22.0
    },
    "56": {
      "echelle_order": 56,
      "model": "sinc2",
      "center_angstrom": 6845.4836756383975,
      "width_angstrom": 154.0640940730832,
      "power": 4.499999999981766,
      "n_spectra_fit": 77,
      "wavelength_min": 6797.534035,
      "wavelength_max": 6906.935088,
      "rest_line_angstrom": 4861.3,
      "line_mask_half_width_angstrom": 22.0
    },
    "61": {
      "echelle_order": 61,
      "model": "sinc2",
      "center_angstrom": 7389.455793649828,
      "width_angstrom": 134.96434492032114,
      "power": 2.471030172871301,
      "n_spectra_fit": 77,
      "wavelength_min": 7336.623746,
      "wavelength_max": 7454.896794,
      "rest_line_angstrom": 4861.3,
      "line_mask_half_width_angstrom": 22.0
    },
    "62": {
      "echelle_order": 62,
      "model": "sinc2",
      "center_angstrom": 7508.3270619510295,
      "width_angstrom": 143.14336654988935,
      "power": 2.7623313882012916,
      "n_spectra_fit": 77,
      "wavelength_min": 7454.732476,
      "wavelength_max": 7575.058414,
      "rest_line_angstrom": 4861.3,
      "line_mask_half_width_angstrom": 22.0
    },
    "66": {
      "echelle_order": 66,
      "model": "sinc2",
      "center_angstrom": 8026.2883819303115,
      "width_angstrom": 199.41337178898726,
      "power": 4.499999996210169,
      "n_spectra_fit": 77,
      "wavelength_min": 7968.429159,
      "wavelength_max": 8097.046687,
      "rest_line_angstrom": 4861.3,
      "line_mask_half_width_angstrom": 22.0
    },
    "67": {
      "echelle_order": 67,
      "model": "sinc2",
      "center_angstrom": 8166.130456919806,
      "width_angstrom": 118.99282579467085,
      "power": 1.3756801720050882,
      "n_spectra_fit": 77,
      "wavelength_min": 8108.118668,
      "wavelength_max": 8238.990139,
      "rest_line_angstrom": 4861.3,
      "line_mask_half_width_angstrom": 22.0
    },
    "68": {
      "echelle_order": 68,
      "model": "sinc2",
      "center_angstrom": 8312.948058371487,
      "width_angstrom": 203.83838169152708,
      "power": 4.499999999980193,
      "n_spectra_fit": 77,
      "wavelength_min": 8252.796518,
      "wavelength_max": 8386.003372,
      "rest_line_angstrom": 4861.3,
      "line_mask_half_width_angstrom": 22.0
    },
    "69": {
      "echelle_order": 69,
      "model": "sinc2",
      "center_angstrom": 8464.458771764746,
      "width_angstrom": 196.09801771220475,
      "power": 4.499999999938674,
      "n_spectra_fit": 77,
      "wavelength_min": 8402.948967,
      "wavelength_max": 8538.43875,
      "rest_line_angstrom": 4861.3,
      "line_mask_half_width_angstrom": 22.0
    },
    "70": {
      "echelle_order": 70,
      "model": "sinc2",
      "center_angstrom": 8619.836351852015,
      "width_angstrom": 208.41347214720014,
      "power": 4.499999999966895,
      "n_spectra_fit": 77,
      "wavelength_min": 8558.446151,
      "wavelength_max": 8696.442453,
      "rest_line_angstrom": 4861.3,
      "line_mask_half_width_angstrom": 22.0
    },
    "71": {
      "echelle_order": 71,
      "model": "sinc2",
      "center_angstrom": 8784.109337983919,
      "width_angstrom": 118.42644347843782,
      "power": 1.200000001235763,
      "n_spectra_fit": 77,
      "wavelength_min": 8719.810514,
      "wavelength_max": 8860.409396,
      "rest_line_angstrom": 4861.3,
      "line_mask_half_width_angstrom": 22.0
    },
    "72": {
      "echelle_order": 72,
      "model": "sinc2",
      "center_angstrom": 8947.76284070623,
      "width_angstrom": 158.06529407110622,
      "power": 2.1164658584653155,
      "n_spectra_fit": 77,
      "wavelength_min": 8887.380474,
      "wavelength_max": 9030.680944,
      "rest_line_angstrom": 4861.3,
      "line_mask_half_width_angstrom": 22.0
    },
    "73": {
      "echelle_order": 73,
      "model": "sinc2",
      "center_angstrom": 9129.665520782204,
      "width_angstrom": 233.766519489329,
      "power": 4.4958688414335555,
      "n_spectra_fit": 77,
      "wavelength_min": 9061.522729,
      "wavelength_max": 9207.631633,
      "rest_line_angstrom": 4861.3,
      "line_mask_half_width_angstrom": 22.0
    },
    "74": {
      "echelle_order": 74,
      "model": "sinc2",
      "center_angstrom": 9275.412664655694,
      "width_angstrom": 269.6729264226002,
      "power": 4.499999999914357,
      "n_spectra_fit": 77,
      "wavelength_min": 9242.630309,
      "wavelength_max": 9391.6594,
      "rest_line_angstrom": 4861.3,
      "line_mask_half_width_angstrom": 22.0
    },
    "75": {
      "echelle_order": 75,
      "model": "sinc2",
      "center_angstrom": 9500.577339068615,
      "width_angstrom": 150.9277556258981,
      "power": 1.3879194838565208,
      "n_spectra_fit": 77,
      "wavelength_min": 9431.130381,
      "wavelength_max": 9583.199248,
      "rest_line_angstrom": 4861.3,
      "line_mask_half_width_angstrom": 22.0
    },
    "76": {
      "echelle_order": 76,
      "model": "sinc2",
      "center_angstrom": 9698.381382419704,
      "width_angstrom": 230.15998231744246,
      "power": 4.499996155535816,
      "n_spectra_fit": 77,
      "wavelength_min": 9627.484243,
      "wavelength_max": 9782.718364,
      "rest_line_angstrom": 4861.3,
      "line_mask_half_width_angstrom": 22.0
    },
    "77": {
      "echelle_order": 77,
      "model": "sinc2",
      "center_angstrom": 9905.818710443307,
      "width_angstrom": 201.90418394808083,
      "power": 2.1765392637368173,
      "n_spectra_fit": 77,
      "wavelength_min": 9832.194156,
      "wavelength_max": 9990.728805,
      "rest_line_angstrom": 4861.3,
      "line_mask_half_width_angstrom": 22.0
    },
    "78": {
      "echelle_order": 78,
      "model": "sinc2",
      "center_angstrom": 10120.242519909416,
      "width_angstrom": 143.12209776095852,
      "power": 1.2000000010953724,
      "n_spectra_fit": 77,
      "wavelength_min": 10045.804317,
      "wavelength_max": 10207.782613,
      "rest_line_angstrom": 4861.3,
      "line_mask_half_width_angstrom": 22.0
    }
  }
}
